{
  "1": {
    "inputs": {
      "model_name": "wd-eva02-large-tagger-v3",
      "dtype": "auto",
      "general_threshold": 0.35,
      "character_threshold": 1,
      "add_rating": false,
      "exclude_tags": "",
      "batch_size": 4,
      "image": [
        "2",
        0
      ]
    },
    "class_type": "WDTimmTagger",
    "_meta": {
      "title": "WD Timm Tagger"
    }
  },
  "2": {
    "inputs": {
      "image": "test.jpg"
    },
    "class_type": "LoadImage",
    "_meta": {
      "title": "画像を読み込む"
    }
  },
  "3": {
    "inputs": {
      "source": [
        "1",
        0
      ]
    },
    "class_type": "PreviewAny",
    "_meta": {
      "title": "プレビュー任意"
    }
  }
}